nuthatch/__init__.py
nuthatch/backend.py
nuthatch/cache.py
nuthatch/cli.py
nuthatch/config.py
nuthatch/memoizer.py
nuthatch/nuthatch.py
nuthatch/processor.py
nuthatch/backends/__init__.py
nuthatch/backends/basic.py
nuthatch/backends/delta.py
nuthatch/backends/parquet.py
nuthatch/backends/sql.py
nuthatch/backends/terracotta.py
nuthatch/backends/zarr.py
nuthatch/processors/__init__.py
nuthatch/processors/timeseries.py
nuthatch-0.3.5.dist-info/METADATA
nuthatch-0.3.5.dist-info/WHEEL
nuthatch-0.3.5.dist-info/entry_points.txt
nuthatch-0.3.5.dist-info/RECORD
