Metadata-Version: 2.3
Name: nuthatch
Version: 0.3.5
Summary: Cacheable big data pipelines
Author-email: Joshua Adkins <josh@rhizaresearch.org>, Genevieve Flaspohler <geneviee@rhizaresearch.org>
License: MIT
Requires-Python: >=3.12
Requires-Dist: click
Requires-Dist: dask-deltatable
Requires-Dist: dask[dataframe]
Requires-Dist: dateparser
Requires-Dist: deltalake==1.1.2
Requires-Dist: fsspec
Requires-Dist: gitpython
Requires-Dist: pandas
Requires-Dist: polars
Requires-Dist: psycopg2-binary
Requires-Dist: pyarrow
Requires-Dist: sqlalchemy
Requires-Dist: terracotta
Requires-Dist: tomli-w
Requires-Dist: xarray
Requires-Dist: zarr
